zotero2wordcloud/__init__.py
zotero2wordcloud/zotero2wordcloud.py
zotero2wordcloud-0.0.1.dist-info/LICENSE
zotero2wordcloud-0.0.1.dist-info/METADATA
zotero2wordcloud-0.0.1.dist-info/WHEEL
zotero2wordcloud-0.0.1.dist-info/top_level.txt
zotero2wordcloud-0.0.1.dist-info/RECORD
