Metadata-Version: 2.1
Name: zotero2wordcloud
Version: 0.0.1
Summary: A package to create a word cloud from a collection of papers in a user's Zotero collection.
Home-page: https://github.com/rgulli/zotero2wordcloud/
Author: Roberto A. Gulli
Author-email: robertoagulli@gmail.com
License: UNKNOWN
Platform: UNKNOWN
Classifier: Programming Language :: Python :: 3.7
Classifier: License :: OSI Approved :: GNU General Public License v3 (GPLv3)
Requires-Dist: wordcloud
Requires-Dist: pyzotero
Requires-Dist: anytree
